COPYING
MANIFEST.in
README.rst
setup.py
CLAMServices.egg-info/PKG-INFO
CLAMServices.egg-info/SOURCES.txt
CLAMServices.egg-info/dependency_links.txt
CLAMServices.egg-info/requires.txt
CLAMServices.egg-info/top_level.txt
clamservices/__init__.py
clamservices/config/__init__.py
clamservices/config/alpino.config.yml
clamservices/config/alpino.py
clamservices/config/colibricore.config.yml
clamservices/config/colibricore.py
clamservices/config/foliastats.config.yml
clamservices/config/foliastats.py
clamservices/config/frog.config.yml
clamservices/config/frog.py
clamservices/config/spacy.config.yml
clamservices/config/spacy.py
clamservices/config/timbl.config.yml
clamservices/config/timbl.py
clamservices/config/ucto.config.yml
clamservices/config/ucto.py
clamservices/wrappers/__init__.py
clamservices/wrappers/alpino_wrapper.py
clamservices/wrappers/colibricore.py
clamservices/wrappers/foliastats.py
clamservices/wrappers/frogwrapper.py
clamservices/wrappers/spacywrapper.py
clamservices/wrappers/timblwrapper.py
clamservices/wrappers/uctowrapper.py
clamservices/wsgi/__init__.py
clamservices/wsgi/alpino.wsgi
clamservices/wsgi/colibricore.wsgi
clamservices/wsgi/foliastats.wsgi
clamservices/wsgi/frog.wsgi
clamservices/wsgi/spacy.wsgi
clamservices/wsgi/timbl.wsgi
clamservices/wsgi/ucto.wsgi