Metadata-Version: 1.1
Name: CLAMServices
Version: 2.2.2
Summary: A collection of CLAM Webservices for various of our NLP tools
Home-page: https://proycon.github.io/clam
Author: Maarten van Gompel
Author-email: proycon@anaproy.nl
License: GPL
Keywords: clam webservice rest nlp computational_linguistics rest
Platform: UNKNOWN
Classifier: Development Status :: 5 - Production/Stable
Classifier: Topic :: Internet :: WWW/HTTP :: WSGI :: Application
Classifier: Topic :: Text Processing :: Linguistic
Classifier: Programming Language :: Python :: 3.3
Classifier: Programming Language :: Python :: 3.4
Classifier: Programming Language :: Python :: 3.5
Classifier: Operating System :: POSIX
Classifier: Intended Audience :: Developers
Classifier: Intended Audience :: Science/Research
Classifier: License :: OSI Approved :: GNU General Public License v3 (GPLv3)
